{"dependencies":[
  {"ecosystem":"npm","name":"@picocss/pico","scope":"dependencies","source":"manifest","path":"app/package.json","line":1},
  {"ecosystem":"npm","name":"@picocss/pico/css/pico.min.css","scope":"import","source":"source","path":"app/src/main.jsx","line":3},
  {"ecosystem":"npm","name":"@playwright/test","scope":"import","source":"source","path":"app/e2e/demo-flow.spec.js","line":1},
  {"ecosystem":"npm","name":"@playwright/test","scope":"import","source":"source","path":"app/e2e/products-ui.spec.js","line":1},
  {"ecosystem":"npm","name":"@playwright/test","scope":"import","source":"source","path":"app/e2e/routes.spec.js","line":1},
  {"ecosystem":"npm","name":"@playwright/test","scope":"devDependencies","source":"manifest","path":"app/package.json","line":1},
  {"ecosystem":"npm","name":"@playwright/test","scope":"import","source":"source","path":"app/playwright.config.js","line":1},
  {"ecosystem":"npm","name":"@supabase/supabase-js","scope":"dependencies","source":"manifest","path":"app/package.json","line":1},
  {"ecosystem":"npm","name":"@supabase/supabase-js","scope":"import","source":"source","path":"app/src/lib/supabase.js","line":1},
  {"ecosystem":"npm","name":"@types/react","scope":"devDependencies","source":"manifest","path":"app/package.json","line":1},
  {"ecosystem":"npm","name":"@types/react-dom","scope":"devDependencies","source":"manifest","path":"app/package.json","line":1},
  {"ecosystem":"npm","name":"@vitejs/plugin-react","scope":"devDependencies","source":"manifest","path":"app/package.json","line":1},
  {"ecosystem":"npm","name":"@vitejs/plugin-react","scope":"import","source":"source","path":"app/vite.config.js","line":2},
  {"ecosystem":"npm","name":"fs","scope":"import","source":"source","path":"app/vite.config.js","line":3},
  {"ecosystem":"npm","name":"jsr:@supabase/functions-js/edge-runtime.d.ts","scope":"import","source":"source","path":"supabase/functions/concierge/index.ts","line":1},
  {"ecosystem":"npm","name":"jsr:@supabase/functions-js/edge-runtime.d.ts","scope":"import","source":"source","path":"supabase/functions/recommend-products/index.ts","line":1},
  {"ecosystem":"npm","name":"lucide-react","scope":"dependencies","source":"manifest","path":"app/package.json","line":1},
  {"ecosystem":"npm","name":"lucide-react","scope":"import","source":"source","path":"app/src/components/Header.jsx","line":1},
  {"ecosystem":"npm","name":"lucide-react","scope":"import","source":"source","path":"app/src/pages/About.jsx","line":1},
  {"ecosystem":"npm","name":"lucide-react","scope":"import","source":"source","path":"app/src/pages/AdminDemo.jsx","line":1},
  {"ecosystem":"npm","name":"lucide-react","scope":"import","source":"source","path":"app/src/pages/Cart.jsx","line":1},
  {"ecosystem":"npm","name":"lucide-react","scope":"import","source":"source","path":"app/src/pages/Checkout.jsx","line":1},
  {"ecosystem":"npm","name":"lucide-react","scope":"import","source":"source","path":"app/src/pages/Complete.jsx","line":1},
  {"ecosystem":"npm","name":"lucide-react","scope":"import","source":"source","path":"app/src/pages/Concierge.jsx","line":1},
  {"ecosystem":"npm","name":"lucide-react","scope":"import","source":"source","path":"app/src/pages/ProductDetail.jsx","line":1},
  {"ecosystem":"npm","name":"lucide-react","scope":"import","source":"source","path":"app/src/pages/Products.jsx","line":1},
  {"ecosystem":"npm","name":"lucide-react","scope":"import","source":"source","path":"app/src/pages/Top.jsx","line":1},
  {"ecosystem":"npm","name":"motion","scope":"dependencies","source":"manifest","path":"app/package.json","line":1},
  {"ecosystem":"npm","name":"motion/react","scope":"import","source":"source","path":"app/src/App.jsx","line":1},
  {"ecosystem":"npm","name":"motion/react","scope":"import","source":"source","path":"app/src/components/FlyingCartItem.jsx","line":1},
  {"ecosystem":"npm","name":"motion/react","scope":"import","source":"source","path":"app/src/components/Header.jsx","line":2},
  {"ecosystem":"npm","name":"motion/react","scope":"import","source":"source","path":"app/src/pages/About.jsx","line":2},
  {"ecosystem":"npm","name":"motion/react","scope":"import","source":"source","path":"app/src/pages/AdminDemo.jsx","line":2},
  {"ecosystem":"npm","name":"motion/react","scope":"import","source":"source","path":"app/src/pages/Concierge.jsx","line":2},
  {"ecosystem":"npm","name":"motion/react","scope":"import","source":"source","path":"app/src/pages/Products.jsx","line":2},
  {"ecosystem":"npm","name":"motion/react","scope":"import","source":"source","path":"app/src/pages/Top.jsx","line":2},
  {"ecosystem":"npm","name":"oxlint","scope":"devDependencies","source":"manifest","path":"app/package.json","line":1},
  {"ecosystem":"npm","name":"path","scope":"import","source":"source","path":"app/vite.config.js","line":4},
  {"ecosystem":"npm","name":"react","scope":"dependencies","source":"manifest","path":"app/package.json","line":1},
  {"ecosystem":"npm","name":"react","scope":"import","source":"source","path":"app/src/components/FlyingCartItem.jsx","line":2},
  {"ecosystem":"npm","name":"react","scope":"import","source":"source","path":"app/src/components/Header.jsx","line":3},
  {"ecosystem":"npm","name":"react","scope":"import","source":"source","path":"app/src/main.jsx","line":1},
  {"ecosystem":"npm","name":"react","scope":"import","source":"source","path":"app/src/pages/AdminDemo.jsx","line":3},
  {"ecosystem":"npm","name":"react","scope":"import","source":"source","path":"app/src/pages/Cart.jsx","line":2},
  {"ecosystem":"npm","name":"react","scope":"import","source":"source","path":"app/src/pages/Checkout.jsx","line":2},
  {"ecosystem":"npm","name":"react","scope":"import","source":"source","path":"app/src/pages/Complete.jsx","line":2},
  {"ecosystem":"npm","name":"react","scope":"import","source":"source","path":"app/src/pages/Concierge.jsx","line":3},
  {"ecosystem":"npm","name":"react","scope":"import","source":"source","path":"app/src/pages/ProductDetail.jsx","line":3},
  {"ecosystem":"npm","name":"react","scope":"import","source":"source","path":"app/src/pages/Products.jsx","line":3},
  {"ecosystem":"npm","name":"react","scope":"import","source":"source","path":"app/src/pages/Top.jsx","line":3},
  {"ecosystem":"npm","name":"react-dom","scope":"dependencies","source":"manifest","path":"app/package.json","line":1},
  {"ecosystem":"npm","name":"react-dom","scope":"import","source":"source","path":"app/src/components/FlyingCartItem.jsx","line":3},
  {"ecosystem":"npm","name":"react-dom/client","scope":"import","source":"source","path":"app/src/main.jsx","line":2},
  {"ecosystem":"npm","name":"react-router-dom","scope":"dependencies","source":"manifest","path":"app/package.json","line":1},
  {"ecosystem":"npm","name":"react-router-dom","scope":"import","source":"source","path":"app/src/App.jsx","line":2},
  {"ecosystem":"npm","name":"react-router-dom","scope":"import","source":"source","path":"app/src/components/Footer.jsx","line":1},
  {"ecosystem":"npm","name":"react-router-dom","scope":"import","source":"source","path":"app/src/components/Header.jsx","line":4},
  {"ecosystem":"npm","name":"react-router-dom","scope":"import","source":"source","path":"app/src/components/TransitionLink.jsx","line":1},
  {"ecosystem":"npm","name":"react-router-dom","scope":"import","source":"source","path":"app/src/pages/About.jsx","line":3},
  {"ecosystem":"npm","name":"react-router-dom","scope":"import","source":"source","path":"app/src/pages/AdminDemo.jsx","line":4},
  {"ecosystem":"npm","name":"react-router-dom","scope":"import","source":"source","path":"app/src/pages/Cart.jsx","line":3},
  {"ecosystem":"npm","name":"react-router-dom","scope":"import","source":"source","path":"app/src/pages/Checkout.jsx","line":3},
  {"ecosystem":"npm","name":"react-router-dom","scope":"import","source":"source","path":"app/src/pages/Complete.jsx","line":3},
  {"ecosystem":"npm","name":"react-router-dom","scope":"import","source":"source","path":"app/src/pages/Concierge.jsx","line":4},
  {"ecosystem":"npm","name":"react-router-dom","scope":"import","source":"source","path":"app/src/pages/Orders.jsx","line":1},
  {"ecosystem":"npm","name":"react-router-dom","scope":"import","source":"source","path":"app/src/pages/ProductDetail.jsx","line":2},
  {"ecosystem":"npm","name":"react-router-dom","scope":"import","source":"source","path":"app/src/pages/Top.jsx","line":4},
  {"ecosystem":"npm","name":"url","scope":"import","source":"source","path":"app/vite.config.js","line":5},
  {"ecosystem":"npm","name":"vite","scope":"devDependencies","source":"manifest","path":"app/package.json","line":1},
  {"ecosystem":"npm","name":"vite","scope":"import","source":"source","path":"app/vite.config.js","line":1}
]}
